irsx/__init__.py
irsx/_version.py
irsx/dir_utils.py
irsx/file_utils.py
irsx/filing.py
irsx/flatten_utils.py
irsx/irsx_cli.py
irsx/irsx_index_cli.py
irsx/irsx_retrieve_cli.py
irsx/keyerror_utils.py
irsx/local_settings-example.py
irsx/log_utils.py
irsx/object_ids.py
irsx/settings.py
irsx/sked_dict_reader.py
irsx/standardizer.py
irsx/text_format_utils.py
irsx/type_utils.py
irsx/xmlrunner.py
irsx/metadata/descriptions.csv
irsx/metadata/groups.csv
irsx/metadata/line_numbers.csv
irsx/metadata/schedule_parts.csv
irsx/metadata/variables.csv
zenitechcyber_irsx-0.2.dist-info/LICENSE
zenitechcyber_irsx-0.2.dist-info/METADATA
zenitechcyber_irsx-0.2.dist-info/WHEEL
zenitechcyber_irsx-0.2.dist-info/entry_points.txt
zenitechcyber_irsx-0.2.dist-info/top_level.txt
zenitechcyber_irsx-0.2.dist-info/RECORD
